pdm_pip_index_url/__init__.py
pdm_pip_index_url/plugin.py
pdm_pip_index_url/utils.py
pdm_pip_index_url-0.1.1.dist-info/METADATA
pdm_pip_index_url-0.1.1.dist-info/WHEEL
pdm_pip_index_url-0.1.1.dist-info/entry_points.txt
pdm_pip_index_url-0.1.1.dist-info/top_level.txt
pdm_pip_index_url-0.1.1.dist-info/RECORD
