Metadata-Version: 2.1
Name: pdm-pip-index-url
Version: 0.1.1
Summary: An automatic converter of PIP_*INDEX_URL to PDM_PYPI_* envs.
Author-email: Kamil Janiec <kamil.p.janiec@gmail.com>
License: MIT
Project-URL: repository, https://github.com/theredfoxlee/pdm-pip-index-url
Requires-Python: >=3.7
